crazyshit/__init__.py
crazyshit/client.py
crazyshit/filters.py
crazyshit/handlers/__init__.py
crazyshit/handlers/on_message.py
crazyshit/methods/__init__.py
crazyshit/methods/esc.py
crazyshit/methods/get_last_message.py
crazyshit/methods/send_message.py
crazyshit/types/update.py
crazyshit-0.0.1.dist-info/LICENSE
crazyshit-0.0.1.dist-info/METADATA
crazyshit-0.0.1.dist-info/WHEEL
crazyshit-0.0.1.dist-info/top_level.txt
crazyshit-0.0.1.dist-info/RECORD
