Metadata-Version: 2.1
Name: crazyshit
Version: 0.0.1
Summary: CrazyShit is a Python library designed for automating tasks for a WhatsApp bot using Selenium. It enables handling of updates and sending messages efficiently.
Author: virus
Project-URL: Homepage, https://github.com/dev-virous/CrazyShit
Project-URL: Issues, https://github.com/dev-virous/CrazyShit/issues
Classifier: Programming Language :: Python :: 3
Classifier: License :: OSI Approved :: MIT License
Classifier: Operating System :: OS Independent
Requires-Python: >=3.8
License-File: LICENSE
Requires-Dist: selenium
Requires-Dist: phonenumbers
Requires-Dist: asyncio
